{
  "buckets": {
    "aw-watcher-window_PC-20250121WKLP": {
      "id": "aw-watcher-window_PC-20250121WKLP",
      "type": "window",
      "events": [
        {
          "id": 263139,
          "timestamp": "2026-06-29T03:50:15.452000+00:00",
          "duration": 585.42,
          "data": {
            "app": "explorer.exe",
            "title": ""
          }
        },
        {
          "id": 263130,
          "timestamp": "2026-06-29T03:36:20.789000+00:00",
          "duration": 833.656,
          "data": {
            "app": "MuMuNxDevice.exe",
            "title": "MuMu安卓设备-1"
          }
        },
        {
          "id": 263129,
          "timestamp": "2026-06-29T03:36:17.772000+00:00",
          "duration": 2.012,
          "data": {
            "app": "explorer.exe",
            "title": ""
          }
        },
        {
          "id": 263128,
          "timestamp": "2026-06-29T03:36:15.762000+00:00",
          "duration": 1.006,
          "data": {
            "app": "MuMuNxDevice.exe",
            "title": "MuMu安卓设备"
          }
        },
        {
          "id": 263127,
          "timestamp": "2026-06-29T03:36:10.736000+00:00",
          "duration": 4.022,
          "data": {
            "app": "alas.exe",
            "title": "Alas"
          }
        },
        {
          "id": 263118,
          "timestamp": "2026-06-29T03:26:54.527000+00:00",
          "duration": 555.206,
          "data": {
            "app": "MuMuNxDevice.exe",
            "title": "MuMu安卓设备"
          }
        },
        {
          "id": 263117,
          "timestamp": "2026-06-29T03:26:53.523000+00:00",
          "duration": 0.0,
          "data": {
            "app": "explorer.exe",
            "title": ""
          }
        },
        {
          "id": 263109,
          "timestamp": "2026-06-29T03:17:18.175000+00:00",
          "duration": 574.345,
          "data": {
            "app": "MuMuNxDevice.exe",
            "title": "MuMu安卓设备"
          }
        },
        {
          "id": 263108,
          "timestamp": "2026-06-29T03:16:10.901000+00:00",
          "duration": 66.271,
          "data": {
            "app": "alas.exe",
            "title": "Alas"
          }
        },
        {
          "id": 263107,
          "timestamp": "2026-06-29T03:11:40.752000+00:00",
          "duration": 269.145,
          "data": {
            "app": "MuMuNxDevice.exe",
            "title": "MuMu安卓设备"
          }
        },
        {
          "id": 263106,
          "timestamp": "2026-06-29T03:11:37.737000+00:00",
          "duration": 2.011,
          "data": {
            "app": "alas.exe",
            "title": "Alas"
          }
        },
        {
          "id": 263105,
          "timestamp": "2026-06-29T03:11:35.723000+00:00",
          "duration": 1.004,
          "data": {
            "app": "MuMuNxDevice.exe",
            "title": "MuMu安卓设备"
          }
        },
        {
          "id": 263104,
          "timestamp": "2026-06-29T03:11:33.713000+00:00",
          "duration": 1.004,
          "data": {
            "app": "MuMuNxDevice.exe",
            "title": "MuMu安卓设备-1"
          }
        },
        {
          "id": 263103,
          "timestamp": "2026-06-29T03:11:29.697000+00:00",
          "duration": 3.012,
          "data": {
            "app": "MAA.exe",
            "title": "MAA (管理员) - v6.13.0#0628 - 衛戍協議：盟約#0626 - MuMu 模拟器 (16416) - 繁中服 (txwy)"
          }
        },
        {
          "id": 263101,
          "timestamp": "2026-06-29T03:09:13.145000+00:00",
          "duration": 135.548,
          "data": {
            "app": "MuMuNxDevice.exe",
            "title": "MuMu安卓设备-1"
          }
        },
        {
          "id": 263099,
          "timestamp": "2026-06-29T03:09:07.115000+00:00",
          "duration": 5.028,
          "data": {
            "app": "MAA.exe",
            "title": "MAA (管理员) - v6.13.0#0628 - 衛戍協議：盟約#0626 - MuMu 模拟器 (16416) - 繁中服 (txwy)"
          }
        },
        {
          "id": 263098,
          "timestamp": "2026-06-29T03:09:03.098000+00:00",
          "duration": 3.013,
          "data": {
            "app": "MuMuNxDevice.exe",
            "title": "MuMu安卓设备-1"
          }
        },
        {
          "id": 263097,
          "timestamp": "2026-06-29T03:08:59.081000+00:00",
          "duration": 3.013,
          "data": {
            "app": "alas.exe",
            "title": "Alas"
          }
        },
        {
          "id": 263071,
          "timestamp": "2026-06-29T01:45:20.709000+00:00",
          "duration": 5017.367,
          "data": {
            "app": "MuMuNxDevice.exe",
            "title": "MuMu安卓设备-1"
          }
        },
        {
          "id": 263070,
          "timestamp": "2026-06-29T01:45:17.696000+00:00",
          "duration": 2.008,
          "data": {
            "app": "MAA.exe",
            "title": "MAA (管理员) - v6.13.0#0628 - 衛戍協議：盟約#0626 - MuMu 模拟器 (16416) - 繁中服 (txwy)"
          }
        },
        {
          "id": 263069,
          "timestamp": "2026-06-29T01:45:00.619000+00:00",
          "duration": 16.073,
          "data": {
            "app": "MuMuNxDevice.exe",
            "title": "MuMu安卓设备-1"
          }
        },
        {
          "id": 263068,
          "timestamp": "2026-06-29T01:44:59.614000+00:00",
          "duration": 0.0,
          "data": {
            "app": "alas.exe",
            "title": "Alas"
          }
        },
        {
          "id": 263067,
          "timestamp": "2026-06-29T01:44:54.588000+00:00",
          "duration": 4.022,
          "data": {
            "app": "MAA.exe",
            "title": "MAA (管理员) - v6.13.0#0628 - 衛戍協議：盟約#0626 - MuMu 模拟器 (16416) - 繁中服 (txwy)"
          }
        },
        {
          "id": 263066,
          "timestamp": "2026-06-29T01:44:53.582000+00:00",
          "duration": 0.0,
          "data": {
            "app": "alas.exe",
            "title": "Alas"
          }
        },
        {
          "id": 263065,
          "timestamp": "2026-06-29T01:44:51.568000+00:00",
          "duration": 1.007,
          "data": {
            "app": "MuMuNxDevice.exe",
            "title": "MuMu安卓设备-1"
          }
        },
        {
          "id": 263033,
          "timestamp": "2026-06-29T00:31:37.337000+00:00",
          "duration": 4393.217,
          "data": {
            "app": "explorer.exe",
            "title": "Program Manager"
          }
        },
        {
          "id": 263032,
          "timestamp": "2026-06-29T00:31:28.293000+00:00",
          "duration": 8.04,
          "data": {
            "app": "MuMuNxDevice.exe",
            "title": "MuMu安卓设备"
          }
        },
        {
          "id": 263031,
          "timestamp": "2026-06-29T00:31:19.247000+00:00",
          "duration": 8.04,
          "data": {
            "app": "MuMuNxDevice.exe",
            "title": "MuMu安卓设备-1"
          }
        },
        {
          "id": 263030,
          "timestamp": "2026-06-29T00:31:18.239000+00:00",
          "duration": 0.0,
          "data": {
            "app": "explorer.exe",
            "title": ""
          }
        },
        {
          "id": 263029,
          "timestamp": "2026-06-29T00:31:17.235000+00:00",
          "duration": 0.0,
          "data": {
            "app": "MAA.exe",
            "title": "MAA (管理员) - v6.13.0#0628 - 衛戍協議：盟約#0626 - MuMu 模拟器 (16416) - 繁中服 (txwy)"
          }
        },
        {
          "id": 263028,
          "timestamp": "2026-06-29T00:31:16.228000+00:00",
          "duration": 0.0,
          "data": {
            "app": "explorer.exe",
            "title": ""
          }
        },
        {
          "id": 263027,
          "timestamp": "2026-06-29T00:31:11.206000+00:00",
          "duration": 4.017,
          "data": {
            "app": "MuMuNxDevice.exe",
            "title": "MuMu安卓设备"
          }
        },
        {
          "id": 263026,
          "timestamp": "2026-06-29T00:31:09.194000+00:00",
          "duration": 1.006,
          "data": {
            "app": "alas.exe",
            "title": "Alas"
          }
        },
        {
          "id": 263025,
          "timestamp": "2026-06-29T00:29:08.700000+00:00",
          "duration": 119.489,
          "data": {
            "app": "MuMuNxDevice.exe",
            "title": "MuMu安卓设备"
          }
        },
        {
          "id": 263024,
          "timestamp": "2026-06-29T00:29:06.692000+00:00",
          "duration": 1.004,
          "data": {
            "app": "MuMuNxDevice.exe",
            "title": "MuMu安卓设备-1"
          }
        },
        {
          "id": 263023,
          "timestamp": "2026-06-29T00:29:00.667000+00:00",
          "duration": 5.022,
          "data": {
            "app": "MAA.exe",
            "title": "MAA (管理员) - v6.13.0#0628 - 衛戍協議：盟約#0626 - MuMu 模拟器 (16416) - 繁中服 (txwy)"
          }
        },
        {
          "id": 263021,
          "timestamp": "2026-06-29T00:28:58.657000+00:00",
          "duration": 1.006,
          "data": {
            "app": "MAA.exe",
            "title": "成就列表"
          }
        },
        {
          "id": 263020,
          "timestamp": "2026-06-29T00:28:53.636000+00:00",
          "duration": 4.018,
          "data": {
            "app": "MAA.exe",
            "title": "MAA (管理员) - v6.13.0#0628 - 衛戍協議：盟約#0626 - MuMu 模拟器 (16416) - 繁中服 (txwy)"
          }
        },
        {
          "id": 263004,
          "timestamp": "2026-06-29T00:07:00.581000+00:00",
          "duration": 1312.051,
          "data": {
            "app": "MuMuNxDevice.exe",
            "title": "MuMu安卓设备-1"
          }
        },
        {
          "id": 263003,
          "timestamp": "2026-06-29T00:06:50.533000+00:00",
          "duration": 9.044,
          "data": {
            "app": "MuMuNxDevice.exe",
            "title": "MuMu安卓设备"
          }
        },
        {
          "id": 263002,
          "timestamp": "2026-06-29T00:06:48.520000+00:00",
          "duration": 1.008,
          "data": {
            "app": "MuMuNxDevice.exe",
            "title": "MuMu安卓设备-1"
          }
        },
        {
          "id": 263001,
          "timestamp": "2026-06-29T00:06:46.510000+00:00",
          "duration": 1.005,
          "data": {
            "app": "MuMuNxDevice.exe",
            "title": "MuMu安卓设备"
          }
        },
        {
          "id": 263000,
          "timestamp": "2026-06-29T00:06:43.495000+00:00",
          "duration": 2.01,
          "data": {
            "app": "MuMuNxDevice.exe",
            "title": "MuMu安卓设备-1"
          }
        },
        {
          "id": 262999,
          "timestamp": "2026-06-29T00:06:38.470000+00:00",
          "duration": 4.021,
          "data": {
            "app": "MuMuNxDevice.exe",
            "title": "MuMu安卓设备"
          }
        },
        {
          "id": 262998,
          "timestamp": "2026-06-29T00:06:37.466000+00:00",
          "duration": 0.0,
          "data": {
            "app": "MuMuNxDevice.exe",
            "title": "MuMu安卓设备-1"
          }
        },
        {
          "id": 262997,
          "timestamp": "2026-06-29T00:06:34.443000+00:00",
          "duration": 2.019,
          "data": {
            "app": "explorer.exe",
            "title": "Program Manager"
          }
        },
        {
          "id": 262996,
          "timestamp": "2026-06-29T00:06:24.381000+00:00",
          "duration": 9.047,
          "data": {
            "app": "ShellExperienceHost.exe",
            "title": "网络连接"
          }
        },
        {
          "id": 262995,
          "timestamp": "2026-06-29T00:06:20.363000+00:00",
          "duration": 3.014,
          "data": {
            "app": "MuMuNxDevice.exe",
            "title": "MuMu安卓设备-1"
          }
        },
        {
          "id": 262994,
          "timestamp": "2026-06-29T00:06:14.335000+00:00",
          "duration": 5.024,
          "data": {
            "app": "MuMuNxDevice.exe",
            "title": "MuMu安卓设备"
          }
        },
        {
          "id": 262993,
          "timestamp": "2026-06-29T00:06:03.287000+00:00",
          "duration": 10.043,
          "data": {
            "app": "MuMuNxDevice.exe",
            "title": "MuMu安卓设备-1"
          }
        },
        {
          "id": 262991,
          "timestamp": "2026-06-29T00:05:59.267000+00:00",
          "duration": 3.015,
          "data": {
            "app": "MuMuNxDevice.exe",
            "title": "MuMu安卓设备"
          }
        },
        {
          "id": 262990,
          "timestamp": "2026-06-29T00:05:57.256000+00:00",
          "duration": 1.007,
          "data": {
            "app": "MuMuNxDevice.exe",
            "title": "MuMu安卓设备-1"
          }
        },
        {
          "id": 262989,
          "timestamp": "2026-06-29T00:05:52.236000+00:00",
          "duration": 4.017,
          "data": {
            "app": "MAA.exe",
            "title": "MAA (管理员) - v6.13.0#0628 - 衛戍協議：盟約#0626 - MuMu 模拟器 (16416) - 繁中服 (txwy)"
          }
        },
        {
          "id": 262988,
          "timestamp": "2026-06-29T00:05:47.213000+00:00",
          "duration": 4.018,
          "data": {
            "app": "MuMuNxDevice.exe",
            "title": "MuMu安卓设备-1"
          }
        },
        {
          "id": 262987,
          "timestamp": "2026-06-29T00:05:45.204000+00:00",
          "duration": 1.005,
          "data": {
            "app": "MuMuNxDevice.exe",
            "title": "MuMu安卓设备"
          }
        },
        {
          "id": 262986,
          "timestamp": "2026-06-29T00:05:36.150000+00:00",
          "duration": 8.051,
          "data": {
            "app": "ShellExperienceHost.exe",
            "title": "网络连接"
          }
        },
        {
          "id": 262867,
          "timestamp": "2026-06-29T00:00:04.236000+00:00",
          "duration": 330.91,
          "data": {
            "app": "MuMuNxDevice.exe",
            "title": "MuMu安卓设备"
          }
        }
      ]
    }
  },
  "export_info": {
    "export_time": "2026-06-29T12:00:06.311147",
    "time_range": {
      "start": "2026-06-29T00:00:04.236960",
      "end": "2026-06-29T12:00:04.236960"
    },
    "total_events": 57
  }
}