{
  "buckets": {
    "aw-watcher-window_PC-20250121WKLP": {
      "id": "aw-watcher-window_PC-20250121WKLP",
      "type": "window",
      "events": [
        {
          "id": 7239,
          "timestamp": "2025-12-02T16:00:01.111000+00:00",
          "duration": 0.0,
          "data": {
            "app": "cmd.exe",
            "title": "C:\\Windows\\SYSTEM32\\cmd.exe"
          }
        },
        {
          "id": 7238,
          "timestamp": "2025-12-02T15:58:48.818000+00:00",
          "duration": 71.29,
          "data": {
            "app": "synthv-studio.exe",
            "title": "Synthesizer V Studio Pro - 术力口周报2025-12第一期test.svp*"
          }
        },
        {
          "id": 7237,
          "timestamp": "2025-12-02T15:58:46.808000+00:00",
          "duration": 1.005,
          "data": {
            "app": "synthv-studio.exe",
            "title": "Synthesizer V Studio Pro - 术力口周报2025-12第一期test.svp"
          }
        },
        {
          "id": 7236,
          "timestamp": "2025-12-02T15:58:15.676000+00:00",
          "duration": 30.127,
          "data": {
            "app": "synthv-studio.exe",
            "title": "Synthesizer V Studio Pro - 术力口周报2025-12第一期test.svp*"
          }
        },
        {
          "id": 7235,
          "timestamp": "2025-12-02T15:58:11.657000+00:00",
          "duration": 3.013,
          "data": {
            "app": "synthv-studio.exe",
            "title": "移调"
          }
        },
        {
          "id": 7234,
          "timestamp": "2025-12-02T15:58:07.638000+00:00",
          "duration": 3.016,
          "data": {
            "app": "synthv-studio.exe",
            "title": "Synthesizer V Studio Pro - 术力口周报2025-12第一期test.svp*"
          }
        },
        {
          "id": 7233,
          "timestamp": "2025-12-02T15:58:04.625000+00:00",
          "duration": 2.009,
          "data": {
            "app": "synthv-studio.exe",
            "title": "移调"
          }
        },
        {
          "id": 7232,
          "timestamp": "2025-12-02T15:57:59.602000+00:00",
          "duration": 4.02,
          "data": {
            "app": "synthv-studio.exe",
            "title": "Synthesizer V Studio Pro - 术力口周报2025-12第一期test.svp*"
          }
        },
        {
          "id": 7231,
          "timestamp": "2025-12-02T15:57:56.589000+00:00",
          "duration": 2.009,
          "data": {
            "app": "synthv-studio.exe",
            "title": "移调"
          }
        },
        {
          "id": 7230,
          "timestamp": "2025-12-02T15:57:49.558000+00:00",
          "duration": 6.027,
          "data": {
            "app": "synthv-studio.exe",
            "title": "Synthesizer V Studio Pro - 术力口周报2025-12第一期test.svp*"
          }
        },
        {
          "id": 7229,
          "timestamp": "2025-12-02T15:57:47.549000+00:00",
          "duration": 1.005,
          "data": {
            "app": "synthv-studio.exe",
            "title": "移调"
          }
        },
        {
          "id": 7228,
          "timestamp": "2025-12-02T15:57:17.426000+00:00",
          "duration": 29.12,
          "data": {
            "app": "synthv-studio.exe",
            "title": "Synthesizer V Studio Pro - 术力口周报2025-12第一期test.svp*"
          }
        },
        {
          "id": 7227,
          "timestamp": "2025-12-02T15:57:16.419000+00:00",
          "duration": 0.0,
          "data": {
            "app": "synthv-studio.exe",
            "title": "Synthesizer V Studio Pro - 术力口周报2025-12第一期test.svp"
          }
        },
        {
          "id": 7226,
          "timestamp": "2025-12-02T15:57:10.392000+00:00",
          "duration": 5.023,
          "data": {
            "app": "synthv-studio.exe",
            "title": "Synthesizer V Studio Pro - 术力口周报2025-12第一期test.svp*"
          }
        },
        {
          "id": 7225,
          "timestamp": "2025-12-02T15:57:08.380000+00:00",
          "duration": 1.006,
          "data": {
            "app": "synthv-studio.exe",
            "title": "Synthesizer V Studio Pro - 术力口周报2025-12第一期test.svp"
          }
        },
        {
          "id": 7224,
          "timestamp": "2025-12-02T15:57:07.375000+00:00",
          "duration": 0.0,
          "data": {
            "app": "synthv-studio.exe",
            "title": "Synthesizer V Studio Pro - 术力口周报2025-12第一期test.svp*"
          }
        },
        {
          "id": 7223,
          "timestamp": "2025-12-02T15:57:06.367000+00:00",
          "duration": 0.0,
          "data": {
            "app": "synthv-studio.exe",
            "title": "Synthesizer V Studio Pro - 术力口周报2025-12第一期test.svp"
          }
        },
        {
          "id": 7222,
          "timestamp": "2025-12-02T15:56:58.335000+00:00",
          "duration": 7.029,
          "data": {
            "app": "synthv-studio.exe",
            "title": "Synthesizer V Studio Pro - 术力口周报2025-12第一期test.svp*"
          }
        },
        {
          "id": 7221,
          "timestamp": "2025-12-02T15:56:56.324000+00:00",
          "duration": 1.005,
          "data": {
            "app": "synthv-studio.exe",
            "title": "Synthesizer V Studio Pro - 术力口周报2025-12第一期test.svp"
          }
        },
        {
          "id": 7219,
          "timestamp": "2025-12-02T15:53:46.535000+00:00",
          "duration": 188.784,
          "data": {
            "app": "synthv-studio.exe",
            "title": "Synthesizer V Studio Pro - 术力口周报2025-12第一期test.svp*"
          }
        },
        {
          "id": 7218,
          "timestamp": "2025-12-02T15:53:42.519000+00:00",
          "duration": 3.011,
          "data": {
            "app": "synthv-studio.exe",
            "title": "Synthesizer V Studio Pro - 术力口周报2025-12第一期test.svp"
          }
        },
        {
          "id": 7217,
          "timestamp": "2025-12-02T15:53:13.403000+00:00",
          "duration": 28.112,
          "data": {
            "app": "synthv-studio.exe",
            "title": "Synthesizer V Studio Pro - 术力口周报2025-12第一期test.svp*"
          }
        },
        {
          "id": 7216,
          "timestamp": "2025-12-02T15:53:12.397000+00:00",
          "duration": 0.0,
          "data": {
            "app": "synthv-studio.exe",
            "title": "Synthesizer V Studio Pro - 术力口周报2025-12第一期test.svp"
          }
        },
        {
          "id": 7215,
          "timestamp": "2025-12-02T15:53:08.379000+00:00",
          "duration": 3.014,
          "data": {
            "app": "synthv-studio.exe",
            "title": "Synthesizer V Studio Pro - 术力口周报2025-12第一期test.svp*"
          }
        },
        {
          "id": 7214,
          "timestamp": "2025-12-02T15:53:07.375000+00:00",
          "duration": 0.0,
          "data": {
            "app": "synthv-studio.exe",
            "title": "Synthesizer V Studio Pro - 术力口周报2025-12第一期test.svp"
          }
        },
        {
          "id": 7213,
          "timestamp": "2025-12-02T15:51:46.040000+00:00",
          "duration": 80.329,
          "data": {
            "app": "synthv-studio.exe",
            "title": "Synthesizer V Studio Pro - 术力口周报2025-12第一期test.svp*"
          }
        },
        {
          "id": 7212,
          "timestamp": "2025-12-02T15:51:44.031000+00:00",
          "duration": 1.005,
          "data": {
            "app": "chrome.exe",
            "title": "SAI2笔刷专项教程+常用笔刷设置推荐 - 哔哩哔哩 - Cent Browser"
          }
        },
        {
          "id": 7210,
          "timestamp": "2025-12-02T15:48:23.199000+00:00",
          "duration": 199.829,
          "data": {
            "app": "synthv-studio.exe",
            "title": "Synthesizer V Studio Pro - 术力口周报2025-12第一期test.svp*"
          }
        },
        {
          "id": 7209,
          "timestamp": "2025-12-02T15:48:21.192000+00:00",
          "duration": 1.004,
          "data": {
            "app": "synthv-studio.exe",
            "title": "Synthesizer V Studio Pro - 术力口周报2025-12第一期test.svp"
          }
        },
        {
          "id": 7208,
          "timestamp": "2025-12-02T15:48:17.173000+00:00",
          "duration": 3.014,
          "data": {
            "app": "synthv-studio.exe",
            "title": "Synthesizer V Studio Pro - 术力口周报2025-12第一期test.svp*"
          }
        },
        {
          "id": 7207,
          "timestamp": "2025-12-02T15:48:15.162000+00:00",
          "duration": 1.007,
          "data": {
            "app": "synthv-studio.exe",
            "title": "Synthesizer V Studio Pro - 术力口周报2025-12第一期test.svp"
          }
        },
        {
          "id": 7205,
          "timestamp": "2025-12-02T15:47:38.002000+00:00",
          "duration": 36.157,
          "data": {
            "app": "synthv-studio.exe",
            "title": "Synthesizer V Studio Pro - 术力口周报2025-12第一期test.svp*"
          }
        },
        {
          "id": 7204,
          "timestamp": "2025-12-02T15:47:34.991000+00:00",
          "duration": 2.007,
          "data": {
            "app": "synthv-studio.exe",
            "title": "Synthesizer V Studio Pro - 术力口周报2025-12第一期test.svp"
          }
        },
        {
          "id": 7203,
          "timestamp": "2025-12-02T15:47:12.899000+00:00",
          "duration": 21.087,
          "data": {
            "app": "synthv-studio.exe",
            "title": "Synthesizer V Studio Pro - 术力口周报2025-12第一期test.svp*"
          }
        },
        {
          "id": 7202,
          "timestamp": "2025-12-02T15:47:11.894000+00:00",
          "duration": 0.0,
          "data": {
            "app": "synthv-studio.exe",
            "title": "Synthesizer V Studio Pro - 术力口周报2025-12第一期test.svp"
          }
        },
        {
          "id": 7201,
          "timestamp": "2025-12-02T15:46:50.801000+00:00",
          "duration": 20.089,
          "data": {
            "app": "synthv-studio.exe",
            "title": "Synthesizer V Studio Pro - 术力口周报2025-12第一期test.svp*"
          }
        },
        {
          "id": 7200,
          "timestamp": "2025-12-02T15:46:49.795000+00:00",
          "duration": 0.0,
          "data": {
            "app": "synthv-studio.exe",
            "title": "Synthesizer V Studio Pro - 术力口周报2025-12第一期test.svp"
          }
        },
        {
          "id": 7199,
          "timestamp": "2025-12-02T15:46:16.652000+00:00",
          "duration": 32.139,
          "data": {
            "app": "synthv-studio.exe",
            "title": "Synthesizer V Studio Pro - 术力口周报2025-12第一期test.svp*"
          }
        },
        {
          "id": 7198,
          "timestamp": "2025-12-02T15:46:14.643000+00:00",
          "duration": 1.005,
          "data": {
            "app": "synthv-studio.exe",
            "title": "Synthesizer V Studio Pro - 术力口周报2025-12第一期test.svp"
          }
        },
        {
          "id": 7197,
          "timestamp": "2025-12-02T15:45:50.545000+00:00",
          "duration": 23.094,
          "data": {
            "app": "synthv-studio.exe",
            "title": "Synthesizer V Studio Pro - 术力口周报2025-12第一期test.svp*"
          }
        },
        {
          "id": 7196,
          "timestamp": "2025-12-02T15:45:47.530000+00:00",
          "duration": 2.011,
          "data": {
            "app": "synthv-studio.exe",
            "title": "Synthesizer V Studio Pro - 术力口周报2025-12第一期test.svp"
          }
        },
        {
          "id": 7194,
          "timestamp": "2025-12-02T15:44:04.100000+00:00",
          "duration": 102.426,
          "data": {
            "app": "synthv-studio.exe",
            "title": "Synthesizer V Studio Pro - 术力口周报2025-12第一期test.svp*"
          }
        },
        {
          "id": 7193,
          "timestamp": "2025-12-02T15:44:02.091000+00:00",
          "duration": 1.004,
          "data": {
            "app": "synthv-studio.exe",
            "title": "Synthesizer V Studio Pro - 术力口周报2025-12第一期test.svp"
          }
        },
        {
          "id": 7192,
          "timestamp": "2025-12-02T15:43:14.897000+00:00",
          "duration": 46.19,
          "data": {
            "app": "synthv-studio.exe",
            "title": "Synthesizer V Studio Pro - 术力口周报2025-12第一期test.svp*"
          }
        },
        {
          "id": 7191,
          "timestamp": "2025-12-02T15:43:13.892000+00:00",
          "duration": 0.0,
          "data": {
            "app": "synthv-studio.exe",
            "title": "Synthesizer V Studio Pro - 术力口周报2025-12第一期test.svp"
          }
        },
        {
          "id": 7190,
          "timestamp": "2025-12-02T15:43:08.870000+00:00",
          "duration": 4.017,
          "data": {
            "app": "synthv-studio.exe",
            "title": "Synthesizer V Studio Pro - 术力口周报2025-12第一期test.svp*"
          }
        },
        {
          "id": 7189,
          "timestamp": "2025-12-02T15:43:07.865000+00:00",
          "duration": 0.0,
          "data": {
            "app": "synthv-studio.exe",
            "title": "Synthesizer V Studio Pro - 术力口周报2025-12第一期test.svp"
          }
        },
        {
          "id": 7188,
          "timestamp": "2025-12-02T15:42:57.824000+00:00",
          "duration": 9.037,
          "data": {
            "app": "synthv-studio.exe",
            "title": "Synthesizer V Studio Pro - 术力口周报2025-12第一期test.svp*"
          }
        },
        {
          "id": 7187,
          "timestamp": "2025-12-02T15:42:56.819000+00:00",
          "duration": 0.0,
          "data": {
            "app": "synthv-studio.exe",
            "title": "Synthesizer V Studio Pro - 术力口周报2025-12第一期test.svp"
          }
        },
        {
          "id": 7185,
          "timestamp": "2025-12-02T15:41:51.528000+00:00",
          "duration": 64.286,
          "data": {
            "app": "synthv-studio.exe",
            "title": "Synthesizer V Studio Pro - 术力口周报2025-12第一期test.svp*"
          }
        },
        {
          "id": 7184,
          "timestamp": "2025-12-02T15:41:49.513000+00:00",
          "duration": 1.008,
          "data": {
            "app": "synthv-studio.exe",
            "title": "Synthesizer V Studio Pro - 术力口周报2025-12第一期test.svp"
          }
        },
        {
          "id": 7183,
          "timestamp": "2025-12-02T15:41:47.504000+00:00",
          "duration": 1.006,
          "data": {
            "app": "synthv-studio.exe",
            "title": "Synthesizer V Studio Pro - 术力口周报2025-12第一期test.svp*"
          }
        },
        {
          "id": 7182,
          "timestamp": "2025-12-02T15:41:44.493000+00:00",
          "duration": 2.007,
          "data": {
            "app": "synthv-studio.exe",
            "title": "Synthesizer V Studio Pro - 术力口周报2025-12第一期test.svp"
          }
        },
        {
          "id": 7181,
          "timestamp": "2025-12-02T15:40:29.192000+00:00",
          "duration": 74.297,
          "data": {
            "app": "synthv-studio.exe",
            "title": "Synthesizer V Studio Pro - 术力口周报2025-12第一期test.svp*"
          }
        },
        {
          "id": 7180,
          "timestamp": "2025-12-02T15:40:26.174000+00:00",
          "duration": 2.012,
          "data": {
            "app": "synthv-studio.exe",
            "title": "Synthesizer V Studio Pro - 术力口周报2025-12第一期test.svp"
          }
        },
        {
          "id": 7179,
          "timestamp": "2025-12-02T15:40:19.142000+00:00",
          "duration": 6.027,
          "data": {
            "app": "synthv-studio.exe",
            "title": "Synthesizer V Studio Pro - 术力口周报2025-12第一期test.svp*"
          }
        },
        {
          "id": 7178,
          "timestamp": "2025-12-02T15:40:17.132000+00:00",
          "duration": 1.006,
          "data": {
            "app": "synthv-studio.exe",
            "title": "Synthesizer V Studio Pro - 术力口周报2025-12第一期test.svp"
          }
        },
        {
          "id": 7177,
          "timestamp": "2025-12-02T15:40:05.080000+00:00",
          "duration": 11.048,
          "data": {
            "app": "synthv-studio.exe",
            "title": "Synthesizer V Studio Pro - 术力口周报2025-12第一期test.svp*"
          }
        },
        {
          "id": 7176,
          "timestamp": "2025-12-02T15:40:04.071000+00:00",
          "duration": 0.0,
          "data": {
            "app": "synthv-studio.exe",
            "title": "Synthesizer V Studio Pro - 术力口周报2025-12第一期test.svp"
          }
        },
        {
          "id": 7175,
          "timestamp": "2025-12-02T15:40:01.056000+00:00",
          "duration": 2.01,
          "data": {
            "app": "synthv-studio.exe",
            "title": "Synthesizer V Studio Pro - 术力口周报2025-12第一期test.svp*"
          }
        },
        {
          "id": 7174,
          "timestamp": "2025-12-02T15:40:00.048000+00:00",
          "duration": 0.0,
          "data": {
            "app": "synthv-studio.exe",
            "title": "Synthesizer V Studio Pro - 术力口周报2025-12第一期test.svp"
          }
        },
        {
          "id": 7172,
          "timestamp": "2025-12-02T15:38:36.696000+00:00",
          "duration": 82.348,
          "data": {
            "app": "synthv-studio.exe",
            "title": "Synthesizer V Studio Pro - 术力口周报2025-12第一期test.svp*"
          }
        },
        {
          "id": 7171,
          "timestamp": "2025-12-02T15:38:35.687000+00:00",
          "duration": 0.0,
          "data": {
            "app": "synthv-studio.exe",
            "title": "Synthesizer V Studio Pro - 术力口周报2025-12第一期test.svp"
          }
        },
        {
          "id": 7170,
          "timestamp": "2025-12-02T15:38:32.675000+00:00",
          "duration": 2.009,
          "data": {
            "app": "synthv-studio.exe",
            "title": "Synthesizer V Studio Pro - 术力口周报2025-12第一期test.svp*"
          }
        },
        {
          "id": 7169,
          "timestamp": "2025-12-02T15:38:31.665000+00:00",
          "duration": 0.0,
          "data": {
            "app": "synthv-studio.exe",
            "title": "Synthesizer V Studio Pro - 术力口周报2025-12第一期test.svp"
          }
        },
        {
          "id": 7168,
          "timestamp": "2025-12-02T15:38:01.539000+00:00",
          "duration": 29.121,
          "data": {
            "app": "synthv-studio.exe",
            "title": "Synthesizer V Studio Pro - 术力口周报2025-12第一期test.svp*"
          }
        },
        {
          "id": 7167,
          "timestamp": "2025-12-02T15:37:56.517000+00:00",
          "duration": 4.017,
          "data": {
            "app": "synthv-studio.exe",
            "title": "Synthesizer V Studio Pro - 术力口周报2025-12第一期test.svp"
          }
        },
        {
          "id": 7166,
          "timestamp": "2025-12-02T15:37:10.324000+00:00",
          "duration": 45.19,
          "data": {
            "app": "synthv-studio.exe",
            "title": "Synthesizer V Studio Pro - 术力口周报2025-12第一期test.svp*"
          }
        },
        {
          "id": 7165,
          "timestamp": "2025-12-02T15:36:43.205000+00:00",
          "duration": 26.114,
          "data": {
            "app": "synthv-studio.exe",
            "title": "Synthesizer V Studio Pro - 术力口周报2025-12第一期test.svp"
          }
        },
        {
          "id": 7164,
          "timestamp": "2025-12-02T15:36:42.199000+00:00",
          "duration": 0.0,
          "data": {
            "app": "synthv-studio.exe",
            "title": "Synthesizer V Studio Pro - 未命名"
          }
        },
        {
          "id": 7163,
          "timestamp": "2025-12-02T15:36:37.176000+00:00",
          "duration": 4.019,
          "data": {
            "app": "synthv-studio.exe",
            "title": "打开..."
          }
        },
        {
          "id": 7162,
          "timestamp": "2025-12-02T15:36:34.162000+00:00",
          "duration": 2.01,
          "data": {
            "app": "synthv-studio.exe",
            "title": "Synthesizer V Studio Pro - 未命名"
          }
        },
        {
          "id": 7161,
          "timestamp": "2025-12-02T15:36:33.157000+00:00",
          "duration": 0.0,
          "data": {
            "app": "synthv-studio.exe",
            "title": "打开项目"
          }
        },
        {
          "id": 7159,
          "timestamp": "2025-12-02T15:34:25.632000+00:00",
          "duration": 126.52,
          "data": {
            "app": "synthv-studio.exe",
            "title": "Synthesizer V Studio Pro - 未命名"
          }
        },
        {
          "id": 7158,
          "timestamp": "2025-12-02T15:34:24.626000+00:00",
          "duration": 0.0,
          "data": {
            "app": "synthv-studio.exe",
            "title": ""
          }
        },
        {
          "id": 7157,
          "timestamp": "2025-12-02T15:34:14.582000+00:00",
          "duration": 9.039,
          "data": {
            "app": "explorer.exe",
            "title": ""
          }
        },
        {
          "id": 7156,
          "timestamp": "2025-12-02T15:34:10.564000+00:00",
          "duration": 3.013,
          "data": {
            "app": "SearchApp.exe",
            "title": "搜索"
          }
        },
        {
          "id": 7155,
          "timestamp": "2025-12-02T15:34:06.544000+00:00",
          "duration": 3.016,
          "data": {
            "app": "QQ.exe",
            "title": "QQ"
          }
        },
        {
          "id": 7154,
          "timestamp": "2025-12-02T15:33:58.511000+00:00",
          "duration": 7.03,
          "data": {
            "app": "explorer.exe",
            "title": ""
          }
        },
        {
          "id": 7153,
          "timestamp": "2025-12-02T15:33:57.506000+00:00",
          "duration": 0.0,
          "data": {
            "app": "chrome.exe",
            "title": "SAI2笔刷专项教程+常用笔刷设置推荐 - 哔哩哔哩 - Cent Browser"
          }
        },
        {
          "id": 7152,
          "timestamp": "2025-12-02T15:33:53.483000+00:00",
          "duration": 3.019,
          "data": {
            "app": "explorer.exe",
            "title": ""
          }
        },
        {
          "id": 7151,
          "timestamp": "2025-12-02T15:33:47.458000+00:00",
          "duration": 5.02,
          "data": {
            "app": "MuMuPlayer.exe",
            "title": "MuMu模拟器12"
          }
        },
        {
          "id": 7150,
          "timestamp": "2025-12-02T15:33:46.453000+00:00",
          "duration": 0.0,
          "data": {
            "app": "unknown",
            "title": ""
          }
        },
        {
          "id": 7149,
          "timestamp": "2025-12-02T15:33:45.381000+00:00",
          "duration": 0.0,
          "data": {
            "app": "OneCommander.exe",
            "title": "OneCommander Window Manager"
          }
        },
        {
          "id": 7148,
          "timestamp": "2025-12-02T15:33:44.376000+00:00",
          "duration": 0.0,
          "data": {
            "app": "explorer.exe",
            "title": "此电脑"
          }
        },
        {
          "id": 7140,
          "timestamp": "2025-12-02T15:26:10.566000+00:00",
          "duration": 452.806,
          "data": {
            "app": "QQ.exe",
            "title": "QQ"
          }
        },
        {
          "id": 7138,
          "timestamp": "2025-12-02T15:26:08.554000+00:00",
          "duration": 1.009,
          "data": {
            "app": "MuMuPlayer.exe",
            "title": "MuMu模拟器12"
          }
        },
        {
          "id": 7137,
          "timestamp": "2025-12-02T15:26:06.545000+00:00",
          "duration": 1.004,
          "data": {
            "app": "alas.exe",
            "title": "Alas"
          }
        },
        {
          "id": 7136,
          "timestamp": "2025-12-02T15:26:00.522000+00:00",
          "duration": 5.019,
          "data": {
            "app": "MuMuPlayer.exe",
            "title": "MuMu模拟器12"
          }
        },
        {
          "id": 7126,
          "timestamp": "2025-12-02T15:09:38.735000+00:00",
          "duration": 980.783,
          "data": {
            "app": "QQ.exe",
            "title": "QQ"
          }
        },
        {
          "id": 7125,
          "timestamp": "2025-12-02T15:09:37.730000+00:00",
          "duration": 0.0,
          "data": {
            "app": "unknown",
            "title": ""
          }
        },
        {
          "id": 7124,
          "timestamp": "2025-12-02T15:08:26.392000+00:00",
          "duration": 70.272,
          "data": {
            "app": "QQ.exe",
            "title": "QQ"
          }
        },
        {
          "id": 7123,
          "timestamp": "2025-12-02T15:08:25.385000+00:00",
          "duration": 0.0,
          "data": {
            "app": "explorer.exe",
            "title": ""
          }
        },
        {
          "id": 7122,
          "timestamp": "2025-12-02T15:08:23.376000+00:00",
          "duration": 1.005,
          "data": {
            "app": "Honeyview32.exe",
            "title": "第一期  > 新建画布1.jpg [1/1] - Honeyview 5.51 (Portable)"
          }
        },
        {
          "id": 7121,
          "timestamp": "2025-12-02T15:08:21.366000+00:00",
          "duration": 1.006,
          "data": {
            "app": "OneCommander.exe",
            "title": "第一期"
          }
        },
        {
          "id": 7120,
          "timestamp": "2025-12-02T15:08:20.361000+00:00",
          "duration": 0.0,
          "data": {
            "app": "OneCommander.exe",
            "title": "术力口周报test"
          }
        },
        {
          "id": 7118,
          "timestamp": "2025-12-02T15:07:10.088000+00:00",
          "duration": 69.27,
          "data": {
            "app": "explorer.exe",
            "title": "此电脑"
          }
        },
        {
          "id": 7117,
          "timestamp": "2025-12-02T15:07:08.079000+00:00",
          "duration": 1.005,
          "data": {
            "app": "Everything.exe",
            "title": "Everything"
          }
        },
        {
          "id": 7116,
          "timestamp": "2025-12-02T15:07:05.065000+00:00",
          "duration": 2.011,
          "data": {
            "app": "explorer.exe",
            "title": "此电脑"
          }
        },
        {
          "id": 7115,
          "timestamp": "2025-12-02T15:07:02.052000+00:00",
          "duration": 2.009,
          "data": {
            "app": "OneCommander.exe",
            "title": "第一期"
          }
        },
        {
          "id": 7114,
          "timestamp": "2025-12-02T15:06:56.030000+00:00",
          "duration": 5.019,
          "data": {
            "app": "Honeyview32.exe",
            "title": "第一期  > 新建画布1.jpg [1/1] - Honeyview 5.51 (Portable)"
          }
        },
        {
          "id": 7113,
          "timestamp": "2025-12-02T15:06:55.026000+00:00",
          "duration": 0.0,
          "data": {
            "app": "Honeyview32.exe",
            "title": "Honeyview 5.51 (Portable)"
          }
        },
        {
          "id": 7112,
          "timestamp": "2025-12-02T15:06:52.008000+00:00",
          "duration": 2.009,
          "data": {
            "app": "OneCommander.exe",
            "title": "第一期"
          }
        },
        {
          "id": 7111,
          "timestamp": "2025-12-02T15:06:51.002000+00:00",
          "duration": 0.0,
          "data": {
            "app": "OneCommander.exe",
            "title": "术力口周报test"
          }
        },
        {
          "id": 7110,
          "timestamp": "2025-12-02T15:06:49.998000+00:00",
          "duration": 0.0,
          "data": {
            "app": "OneCommander.exe",
            "title": "F:\\"
          }
        },
        {
          "id": 7109,
          "timestamp": "2025-12-02T15:06:47.991000+00:00",
          "duration": 1.004,
          "data": {
            "app": "explorer.exe",
            "title": "此电脑"
          }
        },
        {
          "id": 7108,
          "timestamp": "2025-12-02T15:06:45.983000+00:00",
          "duration": 1.004,
          "data": {
            "app": "explorer.exe",
            "title": ""
          }
        },
        {
          "id": 7107,
          "timestamp": "2025-12-02T15:06:43.975000+00:00",
          "duration": 1.004,
          "data": {
            "app": "sai2.exe",
            "title": "PaintTool SAI Ver.2 (64bit) Preview.2023.07.11 - 本地磁盘 (F:) / 术力口周报test / 第一期 / 新建画布1.sai2 (*)"
          }
        },
        {
          "id": 7106,
          "timestamp": "2025-12-02T15:06:39.959000+00:00",
          "duration": 3.011,
          "data": {
            "app": "sai2.exe",
            "title": "JPEG 保存"
          }
        },
        {
          "id": 7105,
          "timestamp": "2025-12-02T15:06:34.938000+00:00",
          "duration": 4.016,
          "data": {
            "app": "sai2.exe",
            "title": "导出"
          }
        },
        {
          "id": 7104,
          "timestamp": "2025-12-02T15:06:23.895000+00:00",
          "duration": 10.039,
          "data": {
            "app": "sai2.exe",
            "title": "PaintTool SAI Ver.2 (64bit) Preview.2023.07.11 - 本地磁盘 (F:) / 术力口周报test / 第一期 / 新建画布1.sai2 (*)"
          }
        },
        {
          "id": 7103,
          "timestamp": "2025-12-02T15:06:19.877000+00:00",
          "duration": 3.013,
          "data": {
            "app": "sai2.exe",
            "title": ""
          }
        },
        {
          "id": 7101,
          "timestamp": "2025-12-02T15:02:39.977000+00:00",
          "duration": 218.895,
          "data": {
            "app": "QQ.exe",
            "title": "QQ"
          }
        },
        {
          "id": 7100,
          "timestamp": "2025-12-02T15:02:36.964000+00:00",
          "duration": 2.008,
          "data": {
            "app": "explorer.exe",
            "title": ""
          }
        },
        {
          "id": 7099,
          "timestamp": "2025-12-02T15:02:35.959000+00:00",
          "duration": 0.0,
          "data": {
            "app": "SearchApp.exe",
            "title": "搜索"
          }
        },
        {
          "id": 7088,
          "timestamp": "2025-12-02T14:34:48.827000+00:00",
          "duration": 1666.127,
          "data": {
            "app": "sai2.exe",
            "title": "PaintTool SAI Ver.2 (64bit) Preview.2023.07.11 - 本地磁盘 (F:) / 术力口周报test / 第一期 / 新建画布1.sai2 (*)"
          }
        },
        {
          "id": 7087,
          "timestamp": "2025-12-02T14:34:43.809000+00:00",
          "duration": 4.015,
          "data": {
            "app": "sai2.exe",
            "title": "更改前景色"
          }
        },
        {
          "id": 7081,
          "timestamp": "2025-12-02T14:17:50.097000+00:00",
          "duration": 1012.708,
          "data": {
            "app": "sai2.exe",
            "title": "PaintTool SAI Ver.2 (64bit) Preview.2023.07.11 - 本地磁盘 (F:) / 术力口周报test / 第一期 / 新建画布1.sai2 (*)"
          }
        },
        {
          "id": 7080,
          "timestamp": "2025-12-02T14:17:43.069000+00:00",
          "duration": 6.024,
          "data": {
            "app": "sai2.exe",
            "title": "PaintTool SAI Ver.2 (64bit) Preview.2023.07.11 - 本地磁盘 (F:) / 术力口周报test / 第一期 / 新建画布1.sai2"
          }
        },
        {
          "id": 7077,
          "timestamp": "2025-12-02T14:17:42.064000+00:00",
          "duration": 0.0,
          "data": {
            "app": "explorer.exe",
            "title": ""
          }
        },
        {
          "id": 7076,
          "timestamp": "2025-12-02T14:17:41.060000+00:00",
          "duration": 0.0,
          "data": {
            "app": "chrome.exe",
            "title": "SAI2笔刷专项教程+常用笔刷设置推荐 - 哔哩哔哩 - Cent Browser"
          }
        },
        {
          "id": 7067,
          "timestamp": "2025-12-02T13:58:32.861000+00:00",
          "duration": 1147.195,
          "data": {
            "app": "explorer.exe",
            "title": ""
          }
        },
        {
          "id": 7066,
          "timestamp": "2025-12-02T13:58:31.854000+00:00",
          "duration": 0.0,
          "data": {
            "app": "MuMuPlayer.exe",
            "title": "MuMu模拟器12"
          }
        },
        {
          "id": 7065,
          "timestamp": "2025-12-02T13:58:25.833000+00:00",
          "duration": 5.018,
          "data": {
            "app": "sai2.exe",
            "title": "PaintTool SAI Ver.2 (64bit) Preview.2023.07.11 - 本地磁盘 (F:) / 术力口周报test / 第一期 / 新建画布1.sai2"
          }
        },
        {
          "id": 7058,
          "timestamp": "2025-12-02T13:38:30.436000+00:00",
          "duration": 1194.392,
          "data": {
            "app": "sai2.exe",
            "title": "PaintTool SAI Ver.2 (64bit) Preview.2023.07.11 - 本地磁盘 (F:) / 术力口周报test / 第一期 / 新建画布1.sai2 (*)"
          }
        },
        {
          "id": 7057,
          "timestamp": "2025-12-02T13:38:29.431000+00:00",
          "duration": 0.0,
          "data": {
            "app": "sai2.exe",
            "title": "更改前景色"
          }
        },
        {
          "id": 7041,
          "timestamp": "2025-12-02T13:04:28.927000+00:00",
          "duration": 2039.5,
          "data": {
            "app": "sai2.exe",
            "title": "PaintTool SAI Ver.2 (64bit) Preview.2023.07.11 - 本地磁盘 (F:) / 术力口周报test / 第一期 / 新建画布1.sai2 (*)"
          }
        },
        {
          "id": 7039,
          "timestamp": "2025-12-02T13:04:27.922000+00:00",
          "duration": 0.0,
          "data": {
            "app": "ShellExperienceHost.exe",
            "title": "OneCommander 的跳转列表"
          }
        },
        {
          "id": 7038,
          "timestamp": "2025-12-02T13:04:26.918000+00:00",
          "duration": 0.0,
          "data": {
            "app": "ShellExperienceHost.exe",
            "title": "localsend_app - 快捷方式 的跳转列表"
          }
        },
        {
          "id": 7024,
          "timestamp": "2025-12-02T12:46:08.782000+00:00",
          "duration": 1097.133,
          "data": {
            "app": "sai2.exe",
            "title": "PaintTool SAI Ver.2 (64bit) Preview.2023.07.11 - 本地磁盘 (F:) / 术力口周报test / 第一期 / 新建画布1.sai2 (*)"
          }
        },
        {
          "id": 7023,
          "timestamp": "2025-12-02T12:46:07.778000+00:00",
          "duration": 0.0,
          "data": {
            "app": "unknown",
            "title": ""
          }
        },
        {
          "id": 7022,
          "timestamp": "2025-12-02T12:46:05.712000+00:00",
          "duration": 1.005,
          "data": {
            "app": "MuMuPlayer.exe",
            "title": "MuMu模拟器12"
          }
        },
        {
          "id": 7021,
          "timestamp": "2025-12-02T12:46:03.704000+00:00",
          "duration": 1.005,
          "data": {
            "app": "chrome.exe",
            "title": "SAI2笔刷专项教程+常用笔刷设置推荐 - 哔哩哔哩 - Cent Browser"
          }
        },
        {
          "id": 7019,
          "timestamp": "2025-12-02T12:46:01.695000+00:00",
          "duration": 1.005,
          "data": {
            "app": "MuMuPlayer.exe",
            "title": "MuMu模拟器12"
          }
        },
        {
          "id": 7018,
          "timestamp": "2025-12-02T12:45:58.681000+00:00",
          "duration": 2.011,
          "data": {
            "app": "chrome.exe",
            "title": "SAI2笔刷专项教程+常用笔刷设置推荐 - 哔哩哔哩 - Cent Browser"
          }
        },
        {
          "id": 7017,
          "timestamp": "2025-12-02T12:45:57.676000+00:00",
          "duration": 0.0,
          "data": {
            "app": "unknown",
            "title": ""
          }
        },
        {
          "id": 7016,
          "timestamp": "2025-12-02T12:45:21.478000+00:00",
          "duration": 35.137,
          "data": {
            "app": "MuMuPlayer.exe",
            "title": "MuMu模拟器12"
          }
        },
        {
          "id": 7015,
          "timestamp": "2025-12-02T12:45:20.474000+00:00",
          "duration": 0.0,
          "data": {
            "app": "alas.exe",
            "title": "Alas"
          }
        },
        {
          "id": 7014,
          "timestamp": "2025-12-02T12:45:14.449000+00:00",
          "duration": 5.021,
          "data": {
            "app": "MuMuPlayer.exe",
            "title": "MuMu模拟器12"
          }
        },
        {
          "id": 7004,
          "timestamp": "2025-12-02T12:10:49.840000+00:00",
          "duration": 2063.606,
          "data": {
            "app": "sai2.exe",
            "title": "PaintTool SAI Ver.2 (64bit) Preview.2023.07.11 - 本地磁盘 (F:) / 术力口周报test / 第一期 / 新建画布1.sai2 (*)"
          }
        },
        {
          "id": 7003,
          "timestamp": "2025-12-02T12:10:44.820000+00:00",
          "duration": 4.017,
          "data": {
            "app": "sai2.exe",
            "title": "PaintTool SAI Ver.2 (64bit) Preview.2023.07.11 - 本地磁盘 (F:) / 术力口周报test / 第一期 / 新建画布1.sai2"
          }
        },
        {
          "id": 7002,
          "timestamp": "2025-12-02T12:10:40.806000+00:00",
          "duration": 3.011,
          "data": {
            "app": "sai2.exe",
            "title": "PaintTool SAI Ver.2 (64bit) Preview.2023.07.11"
          }
        },
        {
          "id": 7001,
          "timestamp": "2025-12-02T12:10:37.795000+00:00",
          "duration": 2.008,
          "data": {
            "app": "Everything.exe",
            "title": "photo - Everything"
          }
        },
        {
          "id": 7000,
          "timestamp": "2025-12-02T12:10:35.785000+00:00",
          "duration": 1.006,
          "data": {
            "app": "sai2.exe",
            "title": "确认保存画布"
          }
        },
        {
          "id": 6999,
          "timestamp": "2025-12-02T12:10:32.772000+00:00",
          "duration": 2.008,
          "data": {
            "app": "sai2.exe",
            "title": "PaintTool SAI Ver.2 (64bit) Preview.2023.07.11 - 本地磁盘 (F:) / 术力口周报test / 第一期 / 新建画布1.sai2 (*)"
          }
        },
        {
          "id": 6998,
          "timestamp": "2025-12-02T12:10:31.768000+00:00",
          "duration": 0.0,
          "data": {
            "app": "sai2.exe",
            "title": "PaintTool SAI Ver.2 (64bit) Preview.2023.07.11 - 本地磁盘 (F:) / 术力口周报test / 第一期 / 新建画布1.sai2"
          }
        },
        {
          "id": 6997,
          "timestamp": "2025-12-02T12:10:30.763000+00:00",
          "duration": 0.0,
          "data": {
            "app": "sai2.exe",
            "title": "PaintTool SAI Ver.2 (64bit) Preview.2023.07.11 - 新建画布1 (*)"
          }
        },
        {
          "id": 6996,
          "timestamp": "2025-12-02T12:10:07.675000+00:00",
          "duration": 22.084,
          "data": {
            "app": "sai2.exe",
            "title": "保存画布"
          }
        },
        {
          "id": 6995,
          "timestamp": "2025-12-02T12:10:02.654000+00:00",
          "duration": 4.018,
          "data": {
            "app": "sai2.exe",
            "title": "PaintTool SAI Ver.2 (64bit) Preview.2023.07.11 - 新建画布1 (*)"
          }
        },
        {
          "id": 6994,
          "timestamp": "2025-12-02T12:09:52.619000+00:00",
          "duration": 9.032,
          "data": {
            "app": "sai2.exe",
            "title": "保存画布"
          }
        },
        {
          "id": 6987,
          "timestamp": "2025-12-02T12:00:05.596000+00:00",
          "duration": 586.019,
          "data": {
            "app": "sai2.exe",
            "title": "PaintTool SAI Ver.2 (64bit) Preview.2023.07.11 - 新建画布1 (*)"
          }
        }
      ]
    }
  },
  "export_info": {
    "export_time": "2025-12-03T00:00:07.619775",
    "time_range": {
      "start": "2025-12-02T12:00:05.596445",
      "end": "2025-12-03T00:00:05.596445"
    },
    "total_events": 151
  }
}